odoo/addons/fieldservice_recurring/README.rst
odoo/addons/fieldservice_recurring/__init__.py
odoo/addons/fieldservice_recurring/__manifest__.py
odoo/addons/fieldservice_recurring/data/ir_sequence.xml
odoo/addons/fieldservice_recurring/data/recurring_cron.xml
odoo/addons/fieldservice_recurring/demo/frequency_demo.xml
odoo/addons/fieldservice_recurring/demo/frequency_set_demo.xml
odoo/addons/fieldservice_recurring/demo/recur_template_demo.xml
odoo/addons/fieldservice_recurring/i18n/de.po
odoo/addons/fieldservice_recurring/i18n/es.po
odoo/addons/fieldservice_recurring/i18n/es_AR.po
odoo/addons/fieldservice_recurring/i18n/es_CL.po
odoo/addons/fieldservice_recurring/i18n/fieldservice_recurring.pot
odoo/addons/fieldservice_recurring/i18n/fr.po
odoo/addons/fieldservice_recurring/i18n/it.po
odoo/addons/fieldservice_recurring/i18n/pt_BR.po
odoo/addons/fieldservice_recurring/i18n/tr.po
odoo/addons/fieldservice_recurring/migrations/14.0.2.0.0/pre-migration.py
odoo/addons/fieldservice_recurring/models/__init__.py
odoo/addons/fieldservice_recurring/models/fsm_frequency.py
odoo/addons/fieldservice_recurring/models/fsm_frequency_set.py
odoo/addons/fieldservice_recurring/models/fsm_order.py
odoo/addons/fieldservice_recurring/models/fsm_recurring.py
odoo/addons/fieldservice_recurring/models/fsm_recurring_template.py
odoo/addons/fieldservice_recurring/models/fsm_team.py
odoo/addons/fieldservice_recurring/readme/CONFIGURE.rst
odoo/addons/fieldservice_recurring/readme/CONTRIBUTORS.rst
odoo/addons/fieldservice_recurring/readme/CREDITS.rst
odoo/addons/fieldservice_recurring/readme/DESCRIPTION.rst
odoo/addons/fieldservice_recurring/readme/INSTALL.rst
odoo/addons/fieldservice_recurring/readme/ROADMAP.rst
odoo/addons/fieldservice_recurring/readme/USAGE.rst
odoo/addons/fieldservice_recurring/security/ir.model.access.csv
odoo/addons/fieldservice_recurring/security/recurring_security.xml
odoo/addons/fieldservice_recurring/security/res_groups.xml
odoo14_addon_fieldservice_recurring-14.0.3.4.0.dist-info/METADATA
odoo14_addon_fieldservice_recurring-14.0.3.4.0.dist-info/WHEEL
odoo14_addon_fieldservice_recurring-14.0.3.4.0.dist-info/top_level.txt
odoo14_addon_fieldservice_recurring-14.0.3.4.0.dist-info/RECORD
